sdh-ci-metrics
setup.cfg
setup.py
SDH_CI_Metrics.egg-info/PKG-INFO
SDH_CI_Metrics.egg-info/SOURCES.txt
SDH_CI_Metrics.egg-info/dependency_links.txt
SDH_CI_Metrics.egg-info/namespace_packages.txt
SDH_CI_Metrics.egg-info/requires.txt
SDH_CI_Metrics.egg-info/top_level.txt
sdh/__init__.py
sdh/metrics/__init__.py
sdh/metrics/ci/__init__.py
sdh/metrics/ci/api.py
sdh/metrics/ci/config.py
sdh/metrics/ci/store.py