Metadata-Version: 1.1
Name: SDH-CI-Metrics
Version: 0.2.7
Summary: A service that calculates a small set of quantitative metrics on data from Jenkins.
Home-page: https://github.com/smartdeveloperhub/sdh-ci-metrics
Author: Fernando Serena
Author-email: fernando.serena@centeropenmiddleware.com
License: Apache 2
Download-URL: https://github.com/smartdeveloperhub/sdh-ci-metrics/tarball/0.2.0
Keywords: linked-data,ontology,path,sdh,metrics
Platform: UNKNOWN
